taskmate/__init__.py
taskmate/config.py
taskmate/models.py
taskmate/storage.py
taskmate/tui/__init__.py
taskmate/tui/edit.py
taskmate/tui/main.py
taskmate/tui/taskapp.tcss
taskmate/tui/taskwidget.py
taskmate-0.1.1.dist-info/LICENCE.txt
taskmate-0.1.1.dist-info/METADATA
taskmate-0.1.1.dist-info/WHEEL
taskmate-0.1.1.dist-info/entry_points.txt
taskmate-0.1.1.dist-info/top_level.txt
taskmate-0.1.1.dist-info/RECORD
